<?xml version="1.0" encoding="UTF-8"?>
<objects serializationModel="Studio.02.01.00">
	<object class="AudioFile" id="{e3b10629-7eba-48a1-90d1-327b67759a3b}">
		<property name="assetPath">
			<value>teleport.mp3</value>
		</property>
		<property name="frequencyInKHz">
			<value>44.0999985</value>
		</property>
		<property name="channelCount">
			<value>2</value>
		</property>
		<property name="length">
			<value>1.3061224489795917</value>
		</property>
		<relationship name="masterAssetFolder">
			<destination>{d7ed58d2-d3ce-4d50-a8d6-72e5c2ecc316}</destination>
		</relationship>
	</object>
</objects>
